navi/__init__.py
navi/cli.py
navi/plugins/__init__.py
navi/plugins/action.py
navi/plugins/add_by_file.py
navi/plugins/agent_group_export.py
navi/plugins/agent_to_db.py
navi/plugins/api_wrapper.py
navi/plugins/compliance_export_csv.py
navi/plugins/config.py
navi/plugins/database.py
navi/plugins/dbconfig.py
navi/plugins/enrich.py
navi/plugins/epss.py
navi/plugins/error_msg.py
navi/plugins/explore.py
navi/plugins/export.py
navi/plugins/fixed_export.py
navi/plugins/move_tags.py
navi/plugins/query_export.py
navi/plugins/query_export_32K.py
navi/plugins/rules.py
navi/plugins/scan.py
navi/plugins/scan_efficentcy.py
navi/plugins/scan_evaluation.py
navi/plugins/send_mail.py
navi/plugins/tag_helper.py
navi/plugins/tagrule_export.py
navi/plugins/th_asset_export.py
navi/plugins/th_compliance_export.py
navi/plugins/th_vuln_export.py
navi/plugins/user_export.py
navi/plugins/was.py
navi/plugins/was_export.py
navi_pro-8.2.2.dist-info/LICENSE
navi_pro-8.2.2.dist-info/METADATA
navi_pro-8.2.2.dist-info/WHEEL
navi_pro-8.2.2.dist-info/entry_points.txt
navi_pro-8.2.2.dist-info/top_level.txt
navi_pro-8.2.2.dist-info/RECORD
