Metadata-Version: 2.1
Name: navi-pro
Version: 8.2.2
Summary: A command-line interface to Tenable.io
Home-page: https://github.com/packetchaos/Navi
Author: Casey Reid
Author-email: itprofguru@gmail.com
License: GNUv3
Keywords: tenable tenableVM navi tio,lumin,navi pro,tvm cli,tenable VM cli,automation,vulnerability management
Platform: UNKNOWN
Classifier: Programming Language :: Python :: 3
Classifier: License :: OSI Approved :: GNU General Public License v3 (GPLv3)
Classifier: Operating System :: OS Independent
Requires-Python: >=3.9
Requires-Dist: Click >=7.0
Requires-Dist: requests >=2.31
Requires-Dist: flask >=2.3.2
Requires-Dist: IPy >=1.0
Requires-Dist: pytenable >=1.4.3
Requires-Dist: arrow >=0.17.0
Requires-Dist: boto3 >=1.17.48
Requires-Dist: pexpect >=4.8.0
Requires-Dist: typing-extensions >=4.0.1
Requires-Dist: pandas >=1.1.5
Requires-Dist: numpy >=1.19.5
Requires-Dist: xlrd >=2.0.1
